fauna_easy/__init__.py
fauna_easy/base_model.py
fauna_easy-0.0.1.dist-info/LICENSE
fauna_easy-0.0.1.dist-info/METADATA
fauna_easy-0.0.1.dist-info/WHEEL
fauna_easy-0.0.1.dist-info/top_level.txt
fauna_easy-0.0.1.dist-info/RECORD
