Metadata-Version: 2.1
Name: fauna-easy
Version: 0.0.1
Summary: A convenient wrapper around faunadb-py that abstracts away FQL code for the database service faunadb.
Home-page: https://github.com/DudeBro249/fauna-easy-py
Author: DudeBro249
License: Apache License 2.0
Platform: UNKNOWN
Classifier: Programming Language :: Python :: 3
Classifier: License :: OSI Approved :: Apache Software License
Classifier: Operating System :: OS Independent
Requires-Python: >=3.6
Requires-Dist: faunadb
Requires-Dist: pydantic
